bindflow/__init__.py
bindflow/_gmx_check.py
bindflow/_version.py
bindflow/cli.py
bindflow/home.py
bindflow/runners.py
bindflow/data/ci_systems/WP6.tar.gz
bindflow/data/ci_systems/config-fep.yml
bindflow/data/ci_systems/config-mmpbsa.yml
bindflow/data/gmx_ff/Slipids_2020.ff.tar.gz
bindflow/data/gmx_ff/amber99sb-star-ildn.ff.tar.gz
bindflow/data/gmx_water_models/water_models.yml
bindflow/data/gmx_water_models/amber/ffnonbonded.itp
bindflow/data/gmx_water_models/amber/ions.itp
bindflow/data/gmx_water_models/amber/spc.itp
bindflow/data/gmx_water_models/amber/spce.itp
bindflow/data/gmx_water_models/amber/tip3p.itp
bindflow/data/gmx_water_models/amber/tip4p.itp
bindflow/data/gmx_water_models/amber/tip4pew.itp
bindflow/data/gmx_water_models/amber/tip5p.itp
bindflow/data/gmx_water_models/amber/watermodels.dat
bindflow/data/gmx_water_models/charmm/ffnonbonded.itp
bindflow/data/gmx_water_models/charmm/ions.itp
bindflow/data/gmx_water_models/charmm/spc.itp
bindflow/data/gmx_water_models/charmm/spce.itp
bindflow/data/gmx_water_models/charmm/tip3p.itp
bindflow/data/gmx_water_models/charmm/tip4p.itp
bindflow/data/gmx_water_models/charmm/tip5p.itp
bindflow/data/gmx_water_models/charmm/tips3p.itp
bindflow/data/gmx_water_models/charmm/watermodels.dat
bindflow/data/gmx_water_models/configurations/spc216.gro
bindflow/data/gmx_water_models/configurations/tip4p.gro
bindflow/data/gmx_water_models/configurations/tip5p.gro
bindflow/data/gmx_water_models/oplsaa/ffnonbonded.itp
bindflow/data/gmx_water_models/oplsaa/ions.itp
bindflow/data/gmx_water_models/oplsaa/spc.itp
bindflow/data/gmx_water_models/oplsaa/spce.itp
bindflow/data/gmx_water_models/oplsaa/tip3p.itp
bindflow/data/gmx_water_models/oplsaa/tip4p.itp
bindflow/data/gmx_water_models/oplsaa/tip4pew.itp
bindflow/data/gmx_water_models/oplsaa/tip5p.itp
bindflow/data/gmx_water_models/oplsaa/tip5pe.itp
bindflow/data/gmx_water_models/oplsaa/watermodels.dat
bindflow/free_energy/__init__.py
bindflow/free_energy/fep_analysis.py
bindflow-0.13.0.post24.dist-info/licenses/LICENSE
bindflow-0.13.0.post24.dist-info/METADATA
bindflow-0.13.0.post24.dist-info/WHEEL
bindflow-0.13.0.post24.dist-info/entry_points.txt
bindflow-0.13.0.post24.dist-info/top_level.txt
bindflow-0.13.0.post24.dist-info/RECORD
