Metadata-Version: 2.4
Name: bindflow
Version: 0.13.0.post24
Summary: A snakemake-based workflow for binding free energy calculations using GROMACS.
Author-email: Alejandro Martínez León <ale94mleon@gmail.com>
Project-URL: Hompage, https://github.com/ale94mleon/BindFlow
Project-URL: Discussions, https://github.com/ale94mleon/BindFlow/discussions
Project-URL: Documentation, https://BindFlow.readthedocs.io/en/latest/
Project-URL: Issues, https://github.com/ale94mleon/BindFlow/issues
Keywords: science,chemistry,biology,drug-design
Classifier: Development Status :: 2 - Pre-Alpha
Classifier: Operating System :: OS Independent
Classifier: Intended Audience :: Science/Research
Classifier: Programming Language :: Python :: 3
Classifier: Topic :: Scientific/Engineering :: Bio-Informatics
Classifier: Topic :: Scientific/Engineering :: Chemistry
Requires-Python: <3.11,>=3.8
License-File: LICENSE
Requires-Dist: alchemlyb>=2.0.0
Requires-Dist: pymbar>=4.0.1
Requires-Dist: MDRestraintsGenerator>=0.2.1
Requires-Dist: numpy
Requires-Dist: pandas
Requires-Dist: mdanalysis
Requires-Dist: TOFF>=0.2.0
Requires-Dist: pyyaml
Requires-Dist: parmed
Provides-Extra: dev
Requires-Dist: pytest; extra == "dev"
Dynamic: license-file
